[
  {
    "id": 1,
    "title": "Home",
    "link": "/",
    "megaMenu": false
  },
  {
    "id": 2,
    "title": "About Me",
    "link": "/about",
    "megaMenu": false,
    "subMenu": false
  },
  {
    "id": 4,
    "title": "My Reel",
    "link": "/my-reel",
    "megaMenu": false
  },
  {
    "id": 3,
    "title": "Portfolio",
    "link": "/portfolio",
    "megaMenu": false
  },
  {
    "id": 5,
    "title": "Photography",
    "link": "/all-photos",
    "megaMenu": false,
    "subMenu": [
      {
        "id": 5.1,
        "title": "NATS ON BASE - QATAR 20223",
        "link": "/photography/qatar-2023"
      },
      {
        "id": 5.2,
        "title": "2023 MLB ALL STAR WEEKEND",
        "link": "/photography/all-star-weekend"
      },
      {
        "id": 5.3,
        "title": "AUGUSTA NATIONAL",
        "link": "/photography/augusta-national"
      },
      {
        "id": 5.4,
        "title": "LIVE MUSIC",
        "link": "/photography/live-music"
      },
      {
        "id": 5.5,
        "title": "TRAVEL",
        "link": "/photography/travel"
      }
    ]
  }
]
